odoo/addons/outgoing_email_by_model/README.rst
odoo/addons/outgoing_email_by_model/__init__.py
odoo/addons/outgoing_email_by_model/__manifest__.py
odoo/addons/outgoing_email_by_model/i18n/it.po
odoo/addons/outgoing_email_by_model/i18n/outgoing_email_by_model.pot
odoo/addons/outgoing_email_by_model/models/__init__.py
odoo/addons/outgoing_email_by_model/models/ir_model.py
odoo/addons/outgoing_email_by_model/models/mail_thread.py
odoo/addons/outgoing_email_by_model/readme/CONFIGURE.rst
odoo/addons/outgoing_email_by_model/readme/CONTRIBUTORS.rst
odoo/addons/outgoing_email_by_model/readme/DESCRIPTION.rst
odoo/addons/outgoing_email_by_model/static/description/icon.png
odoo/addons/outgoing_email_by_model/static/description/index.html
odoo/addons/outgoing_email_by_model/tests/__init__.py
odoo/addons/outgoing_email_by_model/tests/models.py
odoo/addons/outgoing_email_by_model/tests/test_mailserver_by_model.py
odoo/addons/outgoing_email_by_model/views/ir_model.xml
odoo_addon_outgoing_email_by_model-16.0.1.0.0.4.dist-info/METADATA
odoo_addon_outgoing_email_by_model-16.0.1.0.0.4.dist-info/WHEEL
odoo_addon_outgoing_email_by_model-16.0.1.0.0.4.dist-info/top_level.txt
odoo_addon_outgoing_email_by_model-16.0.1.0.0.4.dist-info/RECORD
